acesql.py
acesql-0.1.6.dist-info/LICENSE
acesql-0.1.6.dist-info/METADATA
acesql-0.1.6.dist-info/WHEEL
acesql-0.1.6.dist-info/top_level.txt
acesql-0.1.6.dist-info/RECORD
