Metadata-Version: 2.1
Name: acesql
Version: 0.1.6
Summary: Access to ACE Databases
Home-page: https://git.sonova.com/ACE/acedbpp.git
Author: Cem Bakar
Author-email: cem.bakar@sonova.com
License: UNKNOWN
Platform: UNKNOWN
Classifier: Programming Language :: Python :: 3
Classifier: Programming Language :: Python :: 3.6
Classifier: Programming Language :: Python :: 3.7
Classifier: License :: OSI Approved :: GNU General Public License v2 or later (GPLv2+)
Classifier: Operating System :: OS Independent
License-File: LICENSE
Requires-Dist: pyspark (~=3.1.2)
